hamlette/__init__.py
hamlette/_hamcrest.py
hamlette/asserter.py
hamlette/numeric/__init__.py
hamlette/numeric/is_between.py
hamlette/numeric/is_in_range.py
hamlette/py.typed
hamlette/utils/__init__.py
hamlette/utils/types.py
hamlette-0.1.0.dist-info/METADATA
hamlette-0.1.0.dist-info/WHEEL
hamlette-0.1.0.dist-info/licenses/LICENSE
hamlette-0.1.0.dist-info/RECORD
